{"cameraMode":{"drawMode":0,"name":"Shaded","section":"Shading Mode"},"sceneLighting":false,"audioPlay":false,"sceneViewState":{"showFog":true,"showMaterialUpdate":false,"showSkybox":false,"showFlares":true,"showImageEffects":true,"showParticleSystems":true},"in2DMode":false,"pivot":{"x":-1.4844297170639039,"y":0.34348246455192568,"z":0.2190832495689392},"rotation":{"x":0.18780678510665894,"y":0.709370493888855,"z":-0.20575030148029328,"w":0.6474592685699463},"size":0.7415680289268494,"orthographic":false}